charmarr_lib/testing/__init__.py
charmarr_lib/testing/_arr.py
charmarr_lib/testing/_charmcraft.py
charmarr_lib/testing/_http.py
charmarr_lib/testing/_juju.py
charmarr_lib/testing/_k8s.py
charmarr_lib/testing/_terraform.py
charmarr_lib/testing/_version.py
charmarr_lib/testing/steps/__init__.py
charmarr_lib/testing/steps/arr.py
charmarr_lib/testing/steps/download_client.py
charmarr_lib/testing/steps/gluetun.py
charmarr_lib/testing/steps/mesh.py
charmarr_lib/testing/steps/multimeter.py
charmarr_lib/testing/steps/storage.py
charmarr_lib_testing-0.7.1.dist-info/METADATA
charmarr_lib_testing-0.7.1.dist-info/WHEEL
charmarr_lib_testing-0.7.1.dist-info/RECORD
