Metadata-Version: 2.4
Name: charmarr-lib-testing
Version: 0.7.1
Summary: Testing utilities for Charmarr charms
Author-email: Adhitya Ravi <adhityashan95@gmail.com>
License: LGPL-3.0-or-later
Classifier: Development Status :: 3 - Alpha
Classifier: Framework :: Pytest
Classifier: Intended Audience :: Developers
Classifier: License :: OSI Approved :: GNU Lesser General Public License v3 or later (LGPLv3+)
Classifier: Programming Language :: Python :: 3
Classifier: Programming Language :: Python :: 3.12
Requires-Python: >=3.12
Requires-Dist: jubilant>=1.6
Requires-Dist: ops>=2.0
Requires-Dist: pydantic>=2.0
Requires-Dist: pytest-bdd>=7.0
Requires-Dist: pytest-jubilant>=0.1
Requires-Dist: pytest>=8.0
Requires-Dist: pyyaml>=6.0
Requires-Dist: tenacity>=8.0
Provides-Extra: dev
Requires-Dist: mypy>=1.8; extra == 'dev'
Requires-Dist: pytest-cov>=4.0; extra == 'dev'
Requires-Dist: ruff>=0.1; extra == 'dev'
